hermes_model/__init__.py
hermes_model/logging.py
hermes_model/schemas.py
hermes_model/validation.py
hermes_model/tests/test_logging.py
hermes_model/tests/test_validation.py
hermes_model-1.0.0.dist-info/licenses/LICENSE
hermes_model-1.0.0.dist-info/METADATA
hermes_model-1.0.0.dist-info/WHEEL
hermes_model-1.0.0.dist-info/top_level.txt
hermes_model-1.0.0.dist-info/RECORD
