Metadata-Version: 2.4
Name: hermes-model
Version: 1.0.0
Summary: Interface and documentation on how to create an interface to the HERMES software.
Author: Nicolas Schmid
License:                     GNU AFFERO GENERAL PUBLIC LICENSE
Project-URL: Documentation, https://github.com/swiss-seismological-service/hermes-model
Project-URL: Repository, https://github.com/swiss-seismological-service/hermes-model
Project-URL: Issues, https://github.com/swiss-seismological-service/hermes-model/issues
Classifier: Environment :: Console
Classifier: Intended Audience :: Science/Research
Classifier: Intended Audience :: Education
Classifier: Operating System :: OS Independent
Classifier: License :: OSI Approved :: GNU Affero General Public License v3
Classifier: Programming Language :: Python :: 3
Classifier: Programming Language :: Python :: 3.12
Classifier: Programming Language :: Python :: 3.13
Classifier: Topic :: Scientific/Engineering
Classifier: Topic :: Scientific/Engineering :: Physics
Requires-Python: >=3.12
License-File: LICENSE
Requires-Dist: pydantic
Requires-Dist: seismostats
Requires-Dist: shapely
Provides-Extra: hydws
Requires-Dist: hydws-client; extra == "hydws"
Provides-Extra: dev
Requires-Dist: build; extra == "dev"
Requires-Dist: setuptools-scm; extra == "dev"
Requires-Dist: twine; extra == "dev"
Requires-Dist: pyarrow; extra == "dev"
Requires-Dist: pytest; extra == "dev"
Requires-Dist: isort; extra == "dev"
Requires-Dist: pytest-cov; extra == "dev"
Requires-Dist: tox; extra == "dev"
Requires-Dist: flake8; extra == "dev"
Requires-Dist: responses; extra == "dev"
Dynamic: license-file
